Metadata-Version: 2.1
Name: scroll-of-seals
Version: 0.0.15
Summary: A useful library
Home-page: https://github.com/tuliofalmeida/scroll-of-seals
Author: Túlio F. Almeida
Author-email: tuliofalmeida@hotmail.com
License: MIT
Platform: UNKNOWN
Classifier: Programming Language :: Python :: 3.8
Classifier: License :: OSI Approved :: MIT License
Classifier: Operating System :: OS Independent
License-File: LICENSE
